{
  "blocks": [
    {
      "shape": [
        [
          "🟩",
          "🟩",
          null
        ],
        [
          null,
          "🟩",
          "🟩"
        ]
      ],
      "position": [
        3,
        0
      ],
      "rotation": 3,
      "fixed": false
    }
  ],
  "rows": [
    [
      "⬛",
      "⬛",
      "⬛",
      "⬛",
      "⬛",
      "⬛",
      "⬛",
      "⬛"
    ],
    [
      "⬛",
      "⬛",
      "⬛",
      "⬛",
      "⬛",
      "⬛",
      "⬛",
      "⬛"
    ],
    [
      "⬛",
      "⬛",
      "⬛",
      "⬛",
      "⬛",
      "⬛",
      "⬛",
      "⬛"
    ],
    [
      "⬛",
      "🟩",
      "⬛",
      "⬛",
      "⬛",
      "⬛",
      "⬛",
      "⬛"
    ],
    [
      "🟩",
      "🟩",
      "⬛",
      "⬛",
      "⬛",
      "⬛",
      "⬛",
      "⬛"
    ],
    [
      "🟩",
      "⬛",
      "⬛",
      "⬛",
      "⬛",
      "⬛",
      "⬛",
      "⬛"
    ],
    [
      "⬛",
      "⬛",
      "⬛",
      "⬛",
      "⬛",
      "⬛",
      "⬛",
      "⬛"
    ],
    [
      "⬛",
      "⬛",
      "⬛",
      "⬛",
      "⬛",
      "⬛",
      "⬛",
      "⬛"
    ],
    [
      "⬛",
      "⬛",
      "⬛",
      "⬛",
      "⬛",
      "⬛",
      "⬛",
      "⬛"
    ],
    [
      "⬛",
      "⬛",
      "⬛",
      "⬛",
      "⬛",
      "⬛",
      "⬛",
      "⬛"
    ],
    [
      "⬛",
      "⬛",
      "⬛",
      "⬛",
      "⬛",
      "⬛",
      "⬛",
      "⬛"
    ],
    [
      "⬛",
      "⬛",
      "⬛",
      "⬛",
      "⬛",
      "⬛",
      "⬛",
      "⬛"
    ],
    [
      "⬛",
      "⬛",
      "⬛",
      "⬛",
      "⬛",
      "⬛",
      "⬛",
      "⬛"
    ]
  ]
}